mlflow_token/__init__.py
mlflow_token/mlflow_token.py
mlflow_token-1.1.0.dist-info/entry_points.txt
mlflow_token-1.1.0.dist-info/LICENSE
mlflow_token-1.1.0.dist-info/WHEEL
mlflow_token-1.1.0.dist-info/METADATA
mlflow_token-1.1.0.dist-info/RECORD
