Metadata-Version: 2.1
Name: mlflow-token
Version: 1.1.0
Summary: Command line tool to retreive access token for mlflow instance
Home-page: https://github.com/ncsa/mlflow-token
License: BSD-3-Clause
Author: Ben Galewsky
Author-email: bengal1@illinois.edu
Requires-Python: >=3.8,<4.0
Classifier: License :: OSI Approved :: BSD License
Classifier: Programming Language :: Python :: 3
Classifier: Programming Language :: Python :: 3.8
Classifier: Programming Language :: Python :: 3.9
Classifier: Programming Language :: Python :: 3.10
Classifier: Programming Language :: Python :: 3.11
Requires-Dist: requests (>=2.28.2,<3.0.0)
Project-URL: Repository, https://github.com/ncsa/mlflow-token
